senpy/__init__.py
senpy/account_manager.py
senpy/cli.py
senpy/jobs.py
senpy/notifications.py
senpy/request_utils.py
senpy/user_token.py
notify_me_senpy-0.5.1.dist-info/LICENSE.txt
notify_me_senpy-0.5.1.dist-info/METADATA
notify_me_senpy-0.5.1.dist-info/WHEEL
notify_me_senpy-0.5.1.dist-info/entry_points.txt
notify_me_senpy-0.5.1.dist-info/top_level.txt
notify_me_senpy-0.5.1.dist-info/RECORD
