Metadata-Version: 2.1
Name: notify-me-senpy
Version: 0.5.1
Summary: Simple python tracker
Home-page: https://github.com/magantoine/senpy-package
Author: Notify Me SenPy
Author-email: notify.me.senpy@gmail.com
License: GPLv3
Keywords: PRODUCTIVITY
Classifier: Development Status :: 3 - Alpha
Classifier: Intended Audience :: Developers
Classifier: Topic :: Software Development :: Build Tools
Classifier: License :: OSI Approved :: GNU General Public License v3 (GPLv3)
Classifier: Programming Language :: Python :: 3
Classifier: Programming Language :: Python :: 3.4
Classifier: Programming Language :: Python :: 3.5
Classifier: Programming Language :: Python :: 3.6
License-File: LICENSE.txt
Requires-Dist: colorama (==0.4.4)
Requires-Dist: keyring (==23.2.1)
Requires-Dist: requests (==2.26.0)
Requires-Dist: inquirerpy (==0.3.0)
